SPV/__init__.py
SPV-1.0.0.dist-info/LICENSE.txt
SPV-1.0.0.dist-info/METADATA
SPV-1.0.0.dist-info/WHEEL
SPV-1.0.0.dist-info/top_level.txt
SPV-1.0.0.dist-info/RECORD
