Metadata-Version: 2.1
Name: SPV
Version: 1.0.0
Summary: SPV Secure Password Varification
Home-page: https://github.com/mastercodermerwin/SPV-SecurePasswordVerification-
Author: Merwin
Author-email: <merwinmathews1001@gmail.com>
License: MIT
Project-URL: Bug Tracker, https://github.com/mastercodermerwin/SPV-SecurePasswordVerification-/issues
Keywords: python,secure,password,varification,user,client
Platform: UNKNOWN
Classifier: Development Status :: 1 - Planning
Classifier: Intended Audience :: Developers
Classifier: Programming Language :: Python :: 3
Classifier: Operating System :: Unix
Classifier: Operating System :: MacOS :: MacOS X
Classifier: Operating System :: Microsoft :: Windows
Requires-Dist: cryptography
